Metadata-Version: 1.0
Name: scipion-em-bionotes
Version: 0.1.2
Summary: Scipion 3DBionotes plugin.
Home-page: https://github.com/3dbionotes-community/scipion-bionotes
Author: jrmacias
Author-email: jr.macias@cnb.csic.es
License: UNKNOWN
Keywords: scipion cryoem imageprocessing scipion-2.0 3DBionotes annotations viewer
Platform: UNKNOWN
